lib_version_remla/return_version.py
lib_version_remla-0.0.9.dist-info/LICENSE
lib_version_remla-0.0.9.dist-info/METADATA
lib_version_remla-0.0.9.dist-info/WHEEL
lib_version_remla-0.0.9.dist-info/RECORD
