Metadata-Version: 2.1
Name: lib_version_remla
Version: 0.0.9
Summary: A small package which returns its own version.
Author: Jan
Author-email: j2000.vdm@gmail.com
Requires-Python: >=3.11,<4.0
Classifier: License :: OSI Approved :: MIT License
Classifier: Operating System :: OS Independent
Classifier: Programming Language :: Python :: 3
Classifier: Programming Language :: Python :: 3.11
Classifier: Programming Language :: Python :: 3.12
Requires-Dist: twine (>=5.0.0)
